[
  {
    "Author": "boco-bot",
    "Name": "Action Viewer",
    "InternalName": "actionViewer",
    "Punchline": "View Forays-related info of nearby players",
    "Description": "Use /av to view Forays-related info of nearby players",
    "AssemblyVersion": "0.2.3.1",
    "TestingAssemblyVersion": "0.2.3.1",
    "RepoUrl": "https://github.com/klotterc/ActionViewer",
    "ApplicableVersion": "any",
    "DalamudApiLevel": 10,
    "Tags": [
      "stq"
    ],
    "IconUrl": "https://raw.githubusercontent.com/klotterc/ActionViewer/main/ActionViewer/images/icon.png",
    "DownloadLinkInstall": "https://github.com/klotterc/ActionViewer/releases/download/v0.2.3.1/latest.zip",
    "DownloadLinkTesting": "https://github.com/klotterc/ActionViewer/releases/download/v0.2.3.1/latest.zip",
    "DownloadLinkUpdate": "https://github.com/klotterc/ActionViewer/releases/download/v0.2.3.1/latest.zip"
  }
]
